pydeequalb/__init__.py
pydeequalb/analyzers.py
pydeequalb/anomaly_detection.py
pydeequalb/checks.py
pydeequalb/configs.py
pydeequalb/metrics.py
pydeequalb/pandas_utils.py
pydeequalb/profiles.py
pydeequalb/repository.py
pydeequalb/scala_utils.py
pydeequalb/suggestions.py
pydeequalb/verification.py
pydeequalb-0.0.4.dist-info/LICENSE
pydeequalb-0.0.4.dist-info/WHEEL
pydeequalb-0.0.4.dist-info/METADATA
pydeequalb-0.0.4.dist-info/RECORD
