Metadata-Version: 2.1
Name: pydeequalb
Version: 0.0.4
Summary: PyDeequ - Unit Tests for Data
License: Apache-2.0
Keywords: deequ,pydeequ,data-engineering,data-quality,data-profiling,dataquality,dataunittest,data-unit-tests,data-profilers
Author: Calvin Wang
Author-email: calviwan@amazon.com
Maintainer: Calvin Wang
Maintainer-email: calviwan@amazon.com
Requires-Python: >=3.8,<4
Classifier: Development Status :: 4 - Beta
Classifier: License :: OSI Approved :: Apache Software License
Classifier: Programming Language :: Python :: 3
Classifier: Programming Language :: Python :: 3.8
Classifier: Programming Language :: Python :: 3.9
Classifier: Programming Language :: Python :: 3.10
Classifier: Programming Language :: Python :: 3.11
Classifier: Programming Language :: Python :: 3
Provides-Extra: pyspark
Requires-Dist: numpy (>=1.22)
Requires-Dist: pandas (>=0.23.0)
Requires-Dist: pyspark (>=2.4.7,<3.3.0); extra == "pyspark"
